{
  "_buildCommand2" : {
    "command" : "build",
    "skipDependencies" : false,
    "style" : "buildOnly"
  },
  "buildCommand" : "build",
  "configuredTargets" : [
    {
      "guid" : "bfdfe7dc352907fc980b868725387e987add8fbbd12553af2fc6f71a250cc7d9"
    }
  ],
  "containerPath" : "/Users/alexshapisov/Desktop/TechMeSkills/Защита/Photos/Pods/Pods.xcodeproj",
  "continueBuildingAfterErrors" : false,
  "enableIndexBuildArena" : false,
  "hideShellScriptEnvironment" : false,
  "parameters" : {
    "action" : "build",
    "activeArchitecture" : "arm64",
    "activeRunDestination" : {
      "disableOnlyActiveArch" : false,
      "platform" : "iphonesimulator",
      "sdk" : "iphonesimulator15.0",
      "sdkVariant" : "iphonesimulator",
      "supportedArchitectures" : [
        "arm64",
        "x86_64"
      ],
      "targetArchitecture" : "arm64"
    },
    "arenaInfo" : {
      "buildIntermediatesPath" : "",
      "buildProductsPath" : "",
      "derivedDataPath" : "/Users/alexshapisov/Library/Developer/Xcode/DerivedData",
      "indexDataStoreFolderPath" : "/Users/alexshapisov/Library/Developer/Xcode/DerivedData/Pods-gunexfnncyycxrdoscwegmqpdzxw/Index/DataStore",
      "indexEnableDataStore" : true,
      "indexPCHPath" : "/Users/alexshapisov/Library/Developer/Xcode/DerivedData/Pods-gunexfnncyycxrdoscwegmqpdzxw/Index/PrecompiledHeaders",
      "pchPath" : ""
    },
    "configurationName" : "Debug",
    "overrides" : {
      "synthesized" : {
        "table" : {
          "ASSETCATALOG_FILTER_FOR_DEVICE_MODEL" : "iPhone14,5",
          "ASSETCATALOG_FILTER_FOR_DEVICE_OS_VERSION" : "15.0",
          "BUILD_ACTIVE_RESOURCES_ONLY" : "YES",
          "ENABLE_PREVIEWS" : "NO",
          "TARGET_DEVICE_IDENTIFIER" : "BCEF3E53-79FA-4A1F-8EBA-67E7ADB39011",
          "TARGET_DEVICE_MODEL" : "iPhone14,5",
          "TARGET_DEVICE_OS_VERSION" : "15.0",
          "TARGET_DEVICE_PLATFORM_NAME" : "iphonesimulator"
        }
      }
    }
  },
  "schemeCommand" : "launch",
  "schemeCommand2" : "launch",
  "shouldCollectMetrics" : false,
  "showNonLoggedProgress" : true,
  "useDryRun" : false,
  "useImplicitDependencies" : true,
  "useLegacyBuildLocations" : false,
  "useParallelTargets" : true
}